{
  "topics": [
    {
      "topic": "222156",
      "id": 3
    },
    {
      "topic": "rtt",
      "id": 4
    }
  ],
  "words": [
    {
      "topic": "rtt",
      "eng": "zz",
      "kor": "z",
      "isDone": true,
      "isBookmarked": false,
      "id": 4
    },
    {
      "topic": "222156",
      "eng": "run",
      "kor": "운영하다",
      "isDone": false,
      "isBookmarked": false,
      "id": 5
    },
    {
      "topic": "222156",
      "eng": "fire",
      "kor": " 불사르다",
      "isDone": true,
      "isBookmarked": false,
      "id": 6
    },
    {
      "topic": "rtt",
      "eng": "ew4rt",
      "kor": "erat",
      "isDone": true,
      "isBookmarked": false,
      "id": 7
    },
    {
      "topic": "rtt",
      "eng": "eart",
      "kor": "eart",
      "isDone": false,
      "isBookmarked": false,
      "id": 8
    }
  ]
}